Metadata-Version: 1.0
Name: hsync
Version: 1.0.4
Summary: a file sync tools based http
Home-page: https://github.com/banixc/hsync
Author: banixc
Author-email: banixc@qq.com
License: UNKNOWN
Platform: UNKNOWN
